BatchPlan-0.1.2.dist-info/RECORD
BatchPlan-0.1.2.dist-info/LICENSE
BatchPlan-0.1.2.dist-info/WHEEL
BatchPlan-0.1.2.dist-info/top_level.txt
BatchPlan-0.1.2.dist-info/METADATA
batchplan/mark_floors.py
batchplan/extract_floor_plans.py
batchplan/fixes.py
batchplan/formatters.py
batchplan/__init__.py
batchplan/stylings.py
batchplan/utils.py
batchplan/helper.py
batchplan/_Fixes.so
batchplan/filters.py
batchplan/.dylibs/libTKGeomAlgo.7.7.2.dylib
batchplan/.dylibs/libTKBRep.7.7.2.dylib
batchplan/.dylibs/Python
batchplan/.dylibs/libTKGeomBase.7.7.2.dylib
batchplan/.dylibs/libtbbmalloc.2.11.dylib
batchplan/.dylibs/libTKPrim.7.7.2.dylib
batchplan/.dylibs/libTKOffset.7.7.2.dylib
batchplan/.dylibs/libTKG3d.7.7.2.dylib
batchplan/.dylibs/libTKBool.7.7.2.dylib
batchplan/.dylibs/libTKMesh.7.7.2.dylib
batchplan/.dylibs/libTKG2d.7.7.2.dylib
batchplan/.dylibs/libTKMath.7.7.2.dylib
batchplan/.dylibs/libTKShHealing.7.7.2.dylib
batchplan/.dylibs/libtbb.12.11.dylib
batchplan/.dylibs/libTKernel.7.7.2.dylib
batchplan/.dylibs/libTKBO.7.7.2.dylib
batchplan/.dylibs/libTKTopAlgo.7.7.2.dylib
batchplan/.dylibs/libTKXMesh.7.7.2.dylib
batchplan/.dylibs/libTKHLR.7.7.2.dylib
batchplan/.dylibs/libTKFillet.7.7.2.dylib
batchplan/.dylibs/libTKFeat.7.7.2.dylib
