Metadata-Version: 2.1
Name: BatchPlan
Version: 0.1.2
Summary: BatchPlan: A large scale solution for floor plan extraction
Author-email: Burak Yildiz <0byldz@gmail.com>
License: MIT License
Project-URL: Homepage, https://github.com/byildiz/BatchPlan
Project-URL: Issues, https://github.com/byildiz/BatchPlan/issues
Keywords: batchplan,floorplan,ifc
License-File: LICENSE
Requires-Dist: ifcopenshell
Requires-Dist: pandas
Requires-Dist: shapely
Requires-Dist: matplotlib
Requires-Dist: lark
